automations/__init__.py
automations/admin.py
automations/apps.py
automations/flow.py
automations/models.py
automations/settings.py
automations/urls.py
automations/views.py
automations/cms_automations/__init__.py
automations/cms_automations/admin.py
automations/cms_automations/apps.py
automations/cms_automations/cms_apps.py
automations/cms_automations/cms_plugins.py
automations/cms_automations/models.py
automations/cms_automations/tests.py
automations/cms_automations/views.py
automations/cms_automations/locale/de_DE/LC_MESSAGES/django.mo
automations/cms_automations/locale/de_DE/LC_MESSAGES/django.po
automations/cms_automations/migrations/0001_initial.py
automations/cms_automations/migrations/0002_auto_20210506_1957.py
automations/cms_automations/migrations/0003_auto_20210511_0825.py
automations/cms_automations/migrations/0004_auto_20210511_1042.py
automations/cms_automations/migrations/0005_auto_20211121_1838.py
automations/cms_automations/migrations/__init__.py
automations/cms_automations/templates/automations/cms/empty_template.html
automations/locale/de_DE/LC_MESSAGES/django.mo
automations/locale/de_DE/LC_MESSAGES/django.po
automations/management/__init__.py
automations/management/commands/__init__.py
automations/management/commands/automation_delete_history.py
automations/management/commands/automation_step.py
automations/migrations/0001_initial.py
automations/migrations/0002_auto_20210506_1957.py
automations/migrations/0003_auto_20210511_0825.py
automations/migrations/0004_auto_20210511_1042.py
automations/migrations/0005_automationmodel_key.py
automations/migrations/0006_auto_20211121_1357.py
automations/migrations/__init__.py
automations/templates/base.html
automations/templates/automations/base.html
automations/templates/automations/dashboard.html
automations/templates/automations/error_report.html
automations/templates/automations/form_view.html
automations/templates/automations/history.html
automations/templates/automations/preformatted_traceback.html
django_automations-0.9.4.1.dist-info/LICENSE
django_automations-0.9.4.1.dist-info/METADATA
django_automations-0.9.4.1.dist-info/WHEEL
django_automations-0.9.4.1.dist-info/top_level.txt
django_automations-0.9.4.1.dist-info/RECORD
