Metadata-Version: 2.1
Name: django-automations
Version: 0.9.4.1
Summary: Processes and automations for your Django project
Home-page: https://github.com/fsbraun/django-automations
Author: Fabian Braun
Author-email: fsbraun@gmx.de
License: UNKNOWN
Project-URL: Bug Tracker, https://github.com/fsbraun/django-automations/issues
Project-URL: Documentation, https://django-automations.readthedocs.io/en/latest/
Keywords: django_automations,workflow,automation
Platform: UNKNOWN
Classifier: Development Status :: 5 - Production/Stable
Classifier: Programming Language :: Python
Classifier: Programming Language :: Python :: 3.7
Classifier: Programming Language :: Python :: 3.8
Classifier: Programming Language :: Python :: 3.9
Classifier: Programming Language :: Python :: 3.10
Classifier: Framework :: Django
Classifier: Framework :: Django :: 3.0
Classifier: Framework :: Django :: 3.1
Classifier: Framework :: Django :: 3.2
Classifier: License :: OSI Approved :: MIT License
Classifier: Operating System :: OS Independent
Requires-Python: >=3.7
License-File: LICENSE
Requires-Dist: Django (>=3.0)
